currency_converter/__init__.py
currency_converter/converter.py
sdncenter_currency_converter-0.5.2.dist-info/licenses/LICENSE
sdncenter_currency_converter-0.5.2.dist-info/METADATA
sdncenter_currency_converter-0.5.2.dist-info/WHEEL
sdncenter_currency_converter-0.5.2.dist-info/top_level.txt
sdncenter_currency_converter-0.5.2.dist-info/RECORD
